whatportis/__init__.py
whatportis/cli.py
whatportis/db.py
whatportis/server.py
whatportis/utils.py
whatportis-0.8.2.dist-info/LICENSE.txt
whatportis-0.8.2.dist-info/METADATA
whatportis-0.8.2.dist-info/WHEEL
whatportis-0.8.2.dist-info/entry_points.txt
whatportis-0.8.2.dist-info/top_level.txt
whatportis-0.8.2.dist-info/RECORD
