Metadata-Version: 2.1
Name: whatportis
Version: 0.8.2
Summary: A command to search port names and numbers
Home-page: http://github.com/ncrocfer/whatportis
Author: Nicolas Crocfer
Author-email: ncrocfer@gmail.com
License: UNKNOWN
Platform: UNKNOWN
Classifier: Development Status :: 5 - Production/Stable
Classifier: Environment :: Console
Classifier: Natural Language :: English
Classifier: Intended Audience :: Developers
Classifier: License :: OSI Approved :: MIT License
Classifier: Operating System :: OS Independent
Classifier: Programming Language :: Python
Classifier: Programming Language :: Python :: 3
Classifier: Programming Language :: Python :: 3.6
Classifier: Programming Language :: Python :: 3.7
Classifier: Programming Language :: Python :: 3.8
Classifier: Programming Language :: Python :: 3.9
License-File: LICENSE.txt
Requires-Dist: simplejson (==3.17.2)
Requires-Dist: tinydb (==4.4.0)
Requires-Dist: requests (==2.25.1)
Requires-Dist: prettytable (==2.1.0)
Requires-Dist: click (==8.0.1)
Provides-Extra: dev
Requires-Dist: pytest ; extra == 'dev'
Requires-Dist: tox ; extra == 'dev'
Requires-Dist: black ; extra == 'dev'
Provides-Extra: server
Requires-Dist: flask (==1.1.2) ; extra == 'server'
